Pipeln/VERSION
Pipeln/__init__.py
Pipeln/pipeline.py
pipeln-0.2.11.dist-info/AUTHORS.md
pipeln-0.2.11.dist-info/LICENSE
pipeln-0.2.11.dist-info/METADATA
pipeln-0.2.11.dist-info/WHEEL
pipeln-0.2.11.dist-info/top_level.txt
pipeln-0.2.11.dist-info/RECORD
