Metadata-Version: 2.1
Name: pipeln
Version: 0.2.11
Summary: A Python package to create a custom pipeline
Home-page: https://github.com/Adri-Hdez/Pipeln
Author: Adrián H.S
Author-email: adrihs.dev@gmail.com
License: MIT
License-File: LICENSE
License-File: AUTHORS.md
